ecocode/__init__.py
ecocode/__main__.py
ecocode/analysis.py
ecocode/auditor.py
ecocode/main.py
ecocode/models.py
ecocode/refactoring.py
ecocode/reporter.py
ecocode/scoring.py
ecocode/watcher.py
ecocode-0.1.0.dist-info/METADATA
ecocode-0.1.0.dist-info/WHEEL
ecocode-0.1.0.dist-info/entry_points.txt
ecocode-0.1.0.dist-info/top_level.txt
ecocode-0.1.0.dist-info/RECORD
