Metadata-Version: 2.4
Name: ecocode
Version: 0.1.0
Summary: AI-powered Python code auditor for environmental efficiency
Author: EcoCode Team
License: MIT
Keywords: code-analysis,sustainability,python,efficiency
Classifier: Development Status :: 3 - Alpha
Classifier: Intended Audience :: Developers
Classifier: License :: OSI Approved :: MIT License
Classifier: Programming Language :: Python :: 3
Classifier: Programming Language :: Python :: 3.10
Classifier: Programming Language :: Python :: 3.11
Classifier: Programming Language :: Python :: 3.12
Requires-Python: >=3.10
Requires-Dist: watchdog>=3.0.0
Provides-Extra: dev
Requires-Dist: hypothesis>=6.0.0; extra == "dev"
Requires-Dist: pytest>=7.0.0; extra == "dev"
Requires-Dist: pytest-cov>=4.0.0; extra == "dev"
